HowdenConfig/__init__.py
HowdenConfig/config.py
HowdenConfig/parameter/__init__.py
HowdenConfig/parameter/howdenparser.py
howdenconfig-1.0.6.dist-info/METADATA
howdenconfig-1.0.6.dist-info/WHEEL
howdenconfig-1.0.6.dist-info/RECORD
