Metadata-Version: 2.3
Name: HowdenConfig
Version: 1.0.6
Summary: A simple configuration manager with Pydantic and JSON export.
License: MIT
Keywords: config,configuration,pydantic,json
Author: JesperThoftIllemannJ
Author-email: jesper.jaeger@howdendanmark.dk
Requires-Python: >=3.12
Classifier: License :: OSI Approved :: MIT License
Classifier: Programming Language :: Python :: 3
Classifier: Programming Language :: Python :: 3.12
Classifier: Programming Language :: Python :: 3.13
Requires-Dist: pydantic (>=2.11.7,<3.0.0)
Requires-Dist: toml (>=0.10.2,<0.11.0)
Requires-Dist: types-toml (>=0.10.8.20240310,<0.11.0.0)
Project-URL: Documentation, https://github.com/yourusername/config
Project-URL: Homepage, https://github.com/yourusername/config
Project-URL: Repository, https://github.com/yourusername/config
